<!-- xml reconstructed by Source 2 Viewer - https://valveresourceformat.github.io -->
<root>
	<styles>
		<include src="s2r://panorama/styles/citadel_base_styles.vcss_c" />
		<include src="s2r://panorama/styles/tooltips/citadel_tooltip_progress_bar_delta.vcss_c" />
	</styles>
	<TooltipContents>
		<Panel id="DeltaValues">
			<Label class="previousValue" text="{s:previous_value}" />
			<Panel class="arrow" />
			<Label class="newValue" text="{s:new_value}" />
		</Panel>
		<Label class="bonusType" text="{s:bonus_type}" />
	</TooltipContents>
</root>
