<!-- xml reconstructed by Source 2 Viewer 10.1.0.0 - https://valveresourceformat.github.io -->
<root>
	<styles>
		<include src="s2r://panorama/styles/citadel_base_styles.vcss_c" />
		<include src="s2r://panorama/styles/citadel_hud_modifier_message.vcss_c" />
	</styles>
	<snippets>
		<snippet name="MessageContents">
			<Panel class="Hidden">
				<CitadelHeroImage id="HeroImage" heroimagestyle="minimap_icon" />
				<Image id="AbilityIcon" />
				<Label id="MessageLabel" />
			</Panel>
		</snippet>
	</snippets>
	<CitadelModifierMessage class="ModifierMessage" hittest="false" hittestchildren="false">
		<Panel id="MessagesContainer1" class="MessageContainer" />
		<Panel id="MessagesContainer2" class="MessageContainer" />
		<Panel id="MessagesContainer3" class="MessageContainer" />
		<Panel id="MessagesContainer4" class="MessageContainer" />
	</CitadelModifierMessage>
</root>
